natter/__init__.py
natter/__main__.py
natter/app.py
natter/py.typed
natter/data/__init__.py
natter/data/conversation_data.py
natter/data/locations.py
natter/screens/__init__.py
natter/screens/main.py
natter/screens/save_conversation.py
natter/widgets/__init__.py
natter/widgets/output.py
natter/widgets/user_input.py
natter/widgets/output/__init__.py
natter/widgets/output/assistant.py
natter/widgets/output/conversation.py
natter/widgets/output/error.py
natter/widgets/output/user.py
natter-0.0.4.dist-info/METADATA
natter-0.0.4.dist-info/WHEEL
natter-0.0.4.dist-info/entry_points.txt
natter-0.0.4.dist-info/top_level.txt
natter-0.0.4.dist-info/RECORD
